structor/__init__.py
structor/base_commands.py
structor/custom_exceptions.py
structor/structor.py
structor/utils.py
structor-1.0.4.dist-info/LICENSE
structor-1.0.4.dist-info/METADATA
structor-1.0.4.dist-info/WHEEL
structor-1.0.4.dist-info/entry_points.txt
structor-1.0.4.dist-info/top_level.txt
structor-1.0.4.dist-info/RECORD
