Metadata-Version: 2.1
Name: structor
Version: 1.0.4
Summary: Simple package that allow you to create templates of folders/files structure and generate them from a cli (like done in angular, django, react...)
Home-page: https://github.com/MayasMess/structor
Author: Amayas Messara
Author-email: amayas.messara@gmail.com
License: Copyright (c) 2018 The Python Packaging Authority
Project-URL: Homepage, https://github.com/MayasMess/structor
Keywords: structor,file generator
Classifier: License :: OSI Approved :: MIT License
Classifier: Programming Language :: Python
Classifier: Programming Language :: Python :: 3
Requires-Python: >=3.6
License-File: LICENSE
Requires-Dist: click (>=8.1.3)
Requires-Dist: colorama (>=0.4.6)
Requires-Dist: commonmark (>=0.9.1)
Requires-Dist: Pygments (>=2.14.0)
Requires-Dist: PyYAML (>=6.0)
Requires-Dist: rich (>=12.6.0)
Requires-Dist: shellingham (>=1.5.0.post1)
Requires-Dist: typer (>=0.7.0)
